{
	"configurations" : 
	[
		{
			"directories" : 
			[
				{
					"build" : ".",
					"hasInstallRule" : true,
					"jsonFile" : "directory-.-df50af2fc8bdfc7b3622.json",
					"minimumCMakeVersion" : 
					{
						"string" : "3.12"
					},
					"projectIndex" : 0,
					"source" : ".",
					"targetIndexes" : 
					[
						0,
						1,
						2,
						3
					]
				}
			],
			"name" : "",
			"projects" : 
			[
				{
					"directoryIndexes" : 
					[
						0
					],
					"name" : "my_nav",
					"targetIndexes" : 
					[
						0,
						1,
						2,
						3
					]
				}
			],
			"targets" : 
			[
				{
					"directoryIndex" : 0,
					"id" : "my_nav::@6890427a1f51a3e7e1df",
					"jsonFile" : "target-my_nav-3d7c3eec9977f60d55f2.json",
					"name" : "my_nav",
					"projectIndex" : 0
				},
				{
					"directoryIndex" : 0,
					"id" : "my_nav_uninstall::@6890427a1f51a3e7e1df",
					"jsonFile" : "target-my_nav_uninstall-006d23dd16dc9858f343.json",
					"name" : "my_nav_uninstall",
					"projectIndex" : 0
				},
				{
					"directoryIndex" : 0,
					"id" : "t_main::@6890427a1f51a3e7e1df",
					"jsonFile" : "target-t_main-c57761b7d31bda9e7929.json",
					"name" : "t_main",
					"projectIndex" : 0
				},
				{
					"directoryIndex" : 0,
					"id" : "uninstall::@6890427a1f51a3e7e1df",
					"jsonFile" : "target-uninstall-3bedfca91f9d2d896764.json",
					"name" : "uninstall",
					"projectIndex" : 0
				}
			]
		}
	],
	"kind" : "codemodel",
	"paths" : 
	{
		"build" : "/home/tofu/catkin_ws/build/my_nav",
		"source" : "/home/tofu/catkin_ws/src/my_nav"
	},
	"version" : 
	{
		"major" : 2,
		"minor" : 3
	}
}
